coal_mine/__init__.py
coal_mine/abstract_store.py
coal_mine/business_logic.py
coal_mine/cli.py
coal_mine/crontab_schedule.py
coal_mine/memory_store.py
coal_mine/mongo_store.py
coal_mine/server.py
coal_mine-0.7.1.dist-info/LICENSE
coal_mine-0.7.1.dist-info/METADATA
coal_mine-0.7.1.dist-info/WHEEL
coal_mine-0.7.1.dist-info/entry_points.txt
coal_mine-0.7.1.dist-info/top_level.txt
coal_mine-0.7.1.dist-info/zip-safe
coal_mine-0.7.1.dist-info/RECORD
