Metadata-Version: 2.1
Name: coal_mine
Version: 0.7.1
Summary: Coal Mine - Periodic task execution monitor
Home-page: https://github.com/quantopian/coal-mine
Author: Jonathan Kamens
Author-email: jik+coalmine@kamens.us
License: Apache 2.0
Classifier: Development Status :: 5 - Production/Stable
Classifier: Intended Audience :: System Administrators
Classifier: License :: OSI Approved :: Apache Software License
Classifier: Natural Language :: English
Classifier: Programming Language :: Python
Classifier: Programming Language :: Python :: 3 :: Only
Classifier: Topic :: Internet :: WWW/HTTP :: WSGI :: Server
Classifier: Topic :: System :: Monitoring
Classifier: Topic :: System :: Systems Administration
Requires-Python: >=3.2
License-File: LICENSE
Requires-Dist: certifi >=2022.9.24
Requires-Dist: charset-normalizer <3.4,>=2.0.12
Requires-Dist: crontab <1.1,>=0.23.0
Requires-Dist: dnspython <2.7,>=2.2.1
Requires-Dist: idna <3.8,>=3.3
Requires-Dist: logbook <1.8,>=1.5.3
Requires-Dist: pymongo <4.9,>=3.11.0
Requires-Dist: requests <2.33,>=2.27.1
Requires-Dist: urllib3 <2.3,>=1.26.12
